bonfo/__init__.py
bonfo/cli.py
bonfo/msp/__init__.py
bonfo/msp/board.py
bonfo/msp/codes.py
bonfo/msp/message.py
bonfo/msp/state.py
bonfo/msp/structs/__init__.py
bonfo/msp/structs/adapters.py
bonfo/msp/structs/config.py
bonfo/msp/utils.py
bonfo-0.1.0.dist-info/entry_points.txt
bonfo-0.1.0.dist-info/LICENSE
bonfo-0.1.0.dist-info/WHEEL
bonfo-0.1.0.dist-info/METADATA
bonfo-0.1.0.dist-info/RECORD
